odoo/addons/product_supplierinfo_for_customer_picking/README.rst
odoo/addons/product_supplierinfo_for_customer_picking/__init__.py
odoo/addons/product_supplierinfo_for_customer_picking/__manifest__.py
odoo/addons/product_supplierinfo_for_customer_picking/i18n/de.po
odoo/addons/product_supplierinfo_for_customer_picking/i18n/it.po
odoo/addons/product_supplierinfo_for_customer_picking/i18n/product_supplierinfo_for_customer_picking.pot
odoo/addons/product_supplierinfo_for_customer_picking/i18n/pt_BR.po
odoo/addons/product_supplierinfo_for_customer_picking/models/__init__.py
odoo/addons/product_supplierinfo_for_customer_picking/models/stock_move.py
odoo/addons/product_supplierinfo_for_customer_picking/readme/CONTRIBUTORS.rst
odoo/addons/product_supplierinfo_for_customer_picking/readme/DESCRIPTION.rst
odoo/addons/product_supplierinfo_for_customer_picking/static/description/icon.png
odoo/addons/product_supplierinfo_for_customer_picking/static/description/index.html
odoo/addons/product_supplierinfo_for_customer_picking/tests/__init__.py
odoo/addons/product_supplierinfo_for_customer_picking/tests/test_product_supplierinfo_for_customer_picking.py
odoo/addons/product_supplierinfo_for_customer_picking/views/stock_picking_view.xml
odoo_addon_product_supplierinfo_for_customer_picking-16.0.1.0.0.2.dist-info/METADATA
odoo_addon_product_supplierinfo_for_customer_picking-16.0.1.0.0.2.dist-info/WHEEL
odoo_addon_product_supplierinfo_for_customer_picking-16.0.1.0.0.2.dist-info/top_level.txt
odoo_addon_product_supplierinfo_for_customer_picking-16.0.1.0.0.2.dist-info/RECORD
